LICENSE.txt
monday_sdk/__init__.py
monday_sdk/authentication.py
monday_sdk/graphql_loader.py
monday_sdk/monday.py
README.md
monday_sdk-1.0.10.dist-info/LICENSE.txt
monday_sdk-1.0.10.dist-info/METADATA
monday_sdk-1.0.10.dist-info/WHEEL
monday_sdk-1.0.10.dist-info/RECORD
